tgqSim/__init__.py
tgqSim/connecting_test.py
tgqSim/main.py
tgqSim/test_circuit.py
tgqSim/test_code.py
tgqSim/test_gate.py
tgqSim/test_network.py
tgqSim/tmp.py
tgqSim/vertified.py
tgqSim/backend/config.py
tgqSim/backend/super_conducting.py
tgqSim/circuit/__init__.py
tgqSim/circuit/circuit_test.py
tgqSim/circuit/moment.py
tgqSim/circuit/moment_test.py
tgqSim/circuit/quantum_circuit.py
tgqSim/circuit/quantum_circuit_v3.py
tgqSim/circuit/quantum_circuit_v3_bak.py
tgqSim/circuit/decompose/decompositon_methods.py
tgqSim/circuit/decompose/DQG_reduction/DQGreduction.cpython-312-x86_64-linux-gnu.so
tgqSim/circuit/decompose/DQG_reduction/__init__.cpython-312-x86_64-linux-gnu.so
tgqSim/circuit/decompose/SQG_reduction/SQGreduction.cpython-312-x86_64-linux-gnu.so
tgqSim/circuit/decompose/SQG_reduction/__init__.cpython-312-x86_64-linux-gnu.so
tgqSim/circuit/decompose/compiler/__init__.cpython-312-x86_64-linux-gnu.so
tgqSim/circuit/decompose/compiler/schedular.cpython-312-x86_64-linux-gnu.so
tgqSim/circuit/decompose/compiler/schedular.pyi
tgqSim/circuit/decompose/compiler/transpiler.cpython-312-x86_64-linux-gnu.so
tgqSim/circuit/decompose/compiler/transpiler.pyi
tgqSim/circuit/decompose/first_mapping/__init__.cpython-312-x86_64-linux-gnu.so
tgqSim/circuit/decompose/first_mapping/firstmapping.cpython-312-x86_64-linux-gnu.so
tgqSim/circuit/decompose/first_mapping/physicalqubitselection.cpython-312-x86_64-linux-gnu.so
tgqSim/circuit/decompose/routing/__init__.cpython-312-x86_64-linux-gnu.so
tgqSim/circuit/decompose/routing/heuristic.cpython-312-x86_64-linux-gnu.so
tgqSim/circuit/decompose/routing/routing.cpython-312-x86_64-linux-gnu.so
tgqSim/circuit/decompose/routing/sabre.cpython-312-x86_64-linux-gnu.so
tgqSim/circuit/decompose/schedule/__init__.cpython-312-x86_64-linux-gnu.so
tgqSim/circuit/decompose/schedule/schedulealgorithm.cpython-312-x86_64-linux-gnu.so
tgqSim/circuit/decompose/unitary_decomposition/DQGdecomposition.cpython-312-x86_64-linux-gnu.so
tgqSim-1.6.6.dist-info/LICENSE
tgqSim-1.6.6.dist-info/METADATA
tgqSim-1.6.6.dist-info/WHEEL
tgqSim-1.6.6.dist-info/top_level.txt
tgqSim-1.6.6.dist-info/RECORD
